build_scripts/installer-version.py
chiadoge/__init__.py
chiadoge/pyinstaller.spec
chiadoge/clvm/singleton.py
chiadoge/cmds/__init__.py
chiadoge/cmds/chiadoge.py
chiadoge/cmds/configure.py
chiadoge/cmds/farm.py
chiadoge/cmds/farm_funcs.py
chiadoge/cmds/init.py
chiadoge/cmds/init_funcs.py
chiadoge/cmds/keys.py
chiadoge/cmds/keys_funcs.py
chiadoge/cmds/netspace.py
chiadoge/cmds/netspace_funcs.py
chiadoge/cmds/plotnft.py
chiadoge/cmds/plotnft_funcs.py
chiadoge/cmds/plots.py
chiadoge/cmds/show.py
chiadoge/cmds/start.py
chiadoge/cmds/start_funcs.py
chiadoge/cmds/stop.py
chiadoge/cmds/units.py
chiadoge/cmds/wallet.py
chiadoge/cmds/wallet_funcs.py
chiadoge/consensus/__init__.py
chiadoge/consensus/block_body_validation.py
chiadoge/consensus/block_creation.py
chiadoge/consensus/block_header_validation.py
chiadoge/consensus/block_record.py
chiadoge/consensus/block_rewards.py
chiadoge/consensus/block_root_validation.py
chiadoge/consensus/blockchain.py
chiadoge/consensus/blockchain_interface.py
chiadoge/consensus/coinbase.py
chiadoge/consensus/condition_costs.py
chiadoge/consensus/constants.py
chiadoge/consensus/cost_calculator.py
chiadoge/consensus/default_constants.py
chiadoge/consensus/deficit.py
chiadoge/consensus/difficulty_adjustment.py
chiadoge/consensus/find_fork_point.py
chiadoge/consensus/full_block_to_block_record.py
chiadoge/consensus/get_block_challenge.py
chiadoge/consensus/make_sub_epoch_summary.py
chiadoge/consensus/multiprocess_validation.py
chiadoge/consensus/network_type.py
chiadoge/consensus/pos_quality.py
chiadoge/consensus/pot_iterations.py
chiadoge/consensus/vdf_info_computation.py
chiadoge/daemon/__init__.py
chiadoge/daemon/client.py
chiadoge/daemon/server.py
chiadoge/daemon/windows_signal.py
chiadoge/farmer/__init__.py
chiadoge/farmer/farmer.py
chiadoge/farmer/farmer_api.py
chiadoge/full_node/__init__.py
chiadoge/full_node/block_store.py
chiadoge/full_node/bundle_tools.py
chiadoge/full_node/coin_store.py
chiadoge/full_node/full_node.py
chiadoge-1.2.5.dist-info/LICENSE
chiadoge-1.2.5.dist-info/METADATA
chiadoge-1.2.5.dist-info/WHEEL
chiadoge-1.2.5.dist-info/entry_points.txt
chiadoge-1.2.5.dist-info/top_level.txt
chiadoge-1.2.5.dist-info/RECORD
